[
  {
    "TestEndTime": "2021/9/3 P.M. 05:29:26",
    "TestLength": 1,
    "TotalChars": 299,
    "GoodChars": 277,
    "TotalBack": 12,
    "WrongWords": ["having", "acronym", "the"],
    "WrongChars": [
      "r",
      "r",
      "t",
      "v",
      "i",
      "n",
      "g",
      "Spaces",
      "a",
      "p",
      "m",
      "Spaces",
      "b",
      "t",
      "n",
      "e",
      "b",
      "h",
      "e",
      "Spaces",
      "z",
      "i"
    ]
  },
  {
    "TestEndTime": "2021/9/3 P.M. 05:35:01",
    "TestLength": 1,
    "TotalChars": 249,
    "GoodChars": 232,
    "TotalBack": 17,
    "WrongWords": [],
    "WrongChars": [
      "e",
      "l",
      "l",
      "a",
      "l",
      "i",
      "a",
      "a",
      "l",
      "a",
      "u",
      "s",
      "t",
      "d",
      "b",
      "s",
      "e"
    ]
  },
  {
    "TestEndTime": "2021/9/3 P.M. 05:36:33",
    "TestLength": 1,
    "TotalChars": 304,
    "GoodChars": 292,
    "TotalBack": 11,
    "WrongWords": ["before"],
    "WrongChars": [
      "f",
      "r",
      "Spaces",
      "Spaces",
      "d",
      "n",
      "l",
      "r",
      "m",
      "l",
      "i",
      "s"
    ]
  },
  {
    "TestEndTime": "2021/9/3 P.M. 05:40:06",
    "TestLength": 3,
    "TotalChars": 836,
    "GoodChars": 763,
    "TotalBack": 53,
    "WrongWords": [
      "beautiful",
      "come",
      "herself",
      "distortion",
      "migrating",
      "or",
      "got",
      "ground",
      "casualty"
    ],
    "WrongChars": [
      "t",
      "u",
      "Spaces",
      "Spaces",
      "Spaces",
      "Spaces",
      "h",
      "c",
      "j",
      "u",
      "j",
      "s",
      "w",
      "c",
      "c",
      "h",
      "g",
      "e",
      "h",
      "s",
      "c",
      "i",
      "a",
      "b",
      "t",
      "a",
      "k",
      "o",
      "r",
      "b",
      "y",
      "t",
      "s",
      "d",
      "o",
      "n",
      "Spaces",
      "n",
      "e",
      "i",
      "n",
      "g",
      "Spaces",
      "r",
      "t",
      "e",
      "m",
      "a",
      "e",
      "a",
      "r",
      "t",
      "o",
      "r",
      "n",
      "d",
      "x",
      "l",
      "a",
      "i",
      "r",
      "y",
      "s",
      "u",
      "a",
      "l",
      "t",
      "y",
      "Spaces",
      "i",
      "h",
      "m",
      "i"
    ]
  },
  {
    "TestEndTime": "2021/9/3 P.M. 06:19:39",
    "TestLength": 5,
    "TotalChars": 1499,
    "GoodChars": 1432,
    "TotalBack": 59,
    "WrongWords": [
      "idiosyncratic",
      "prenatal",
      "a",
      "coast",
      "ground",
      "fellowship"
    ],
    "WrongChars": [
      "m",
      "n",
      "d",
      "i",
      "s",
      "e",
      "e",
      "i",
      "l",
      "a",
      "a",
      "p",
      "e",
      "d",
      "y",
      "n",
      "n",
      "m",
      "s",
      "r",
      "e",
      "t",
      "e",
      "m",
      "r",
      "e",
      "t",
      "e",
      "a",
      "t",
      "a",
      "o",
      "a",
      "h",
      "g",
      "y",
      "a",
      "c",
      "i",
      "s",
      "Spaces",
      "u",
      "o",
      "n",
      "d",
      "o",
      "a",
      "a",
      "f",
      "u",
      "e",
      "Spaces",
      "e",
      "h",
      "w",
      "b",
      "Spaces",
      "s",
      "e",
      "s",
      "i",
      "c",
      "i",
      "r",
      "b",
      "f",
      "p"
    ]
  },
  {
    "TestEndTime": "2021/9/3 P.M. 06:23:15",
    "TestLength": 2,
    "TotalChars": 580,
    "GoodChars": 548,
    "TotalBack": 25,
    "WrongWords": ["from", "he", "that"],
    "WrongChars": [
      "e",
      "e",
      "v",
      "l",
      "s",
      "e",
      "v",
      "c",
      "d",
      "f",
      "r",
      "o",
      "m",
      "e",
      "Spaces",
      "e",
      "e",
      "i",
      "l",
      "f",
      "c",
      "h",
      "r",
      "y",
      "o",
      "t",
      "h",
      "Spaces",
      "r",
      "e",
      "t",
      "h"
    ]
  },
  {
    "TestEndTime": "2021/9/3 P.M. 08:36:46",
    "TestLength": 3,
    "TotalChars": 888,
    "GoodChars": 837,
    "TotalBack": 41,
    "WrongWords": [
      "favorite",
      "potential",
      "have",
      "system",
      "something",
      "society"
    ],
    "WrongChars": [
      "v",
      "a",
      "f",
      "t",
      "r",
      "l",
      "s",
      "n",
      "e",
      "s",
      "s",
      "r",
      "g",
      "r",
      "g",
      "v",
      "e",
      "p",
      "m",
      "o",
      "c",
      "n",
      "i",
      "s",
      "d",
      "a",
      "r",
      "p",
      "a",
      "e",
      "m",
      "n",
      "g",
      "b",
      "c",
      "l",
      "c",
      "h",
      "i",
      "a",
      "h",
      "t",
      "n",
      "a",
      "o",
      "e",
      "e",
      "e",
      "i",
      "i",
      "e"
    ]
  },
  {
    "TestEndTime": "2021/9/3 P.M. 08:41:24",
    "TestLength": 3,
    "TotalChars": 931,
    "GoodChars": 876,
    "TotalBack": 34,
    "WrongWords": [
      "fashion",
      "all",
      "events",
      "to",
      "portrait",
      "search",
      "area",
      "or",
      "instrument",
      "in",
      "something"
    ],
    "WrongChars": [
      "i",
      "r",
      "n",
      "Spaces",
      "i",
      "a",
      "l",
      "m",
      "p",
      "s",
      "r",
      "o",
      "Spaces",
      "Spaces",
      "c",
      "a",
      "v",
      "n",
      "t",
      "s",
      "x",
      "a",
      "e",
      "t",
      "Spaces",
      "m",
      "a",
      "a",
      "r",
      "e",
      "w",
      "s",
      "e",
      "u",
      "o",
      "r",
      "a",
      "c",
      "h",
      "a",
      "r",
      "e",
      "r",
      "Spaces",
      "n",
      "t",
      "e",
      "g",
      "a",
      "p",
      "n",
      "Spaces",
      "n",
      "g",
      "e"
    ]
  },
  {
    "TestEndTime": "2021/9/3 P.M. 08:48:00",
    "TestLength": 5,
    "TotalChars": 1451,
    "GoodChars": 1361,
    "TotalBack": 65,
    "WrongWords": [
      "into",
      "difficult",
      "and",
      "dispute",
      "times",
      "to",
      "describe",
      "medicinal",
      "belongings",
      "regularly",
      "hard",
      "utterly",
      "action"
    ],
    "WrongChars": [
      "o",
      "a",
      "p",
      "r",
      "p",
      "i",
      "Spaces",
      "Spaces",
      "n",
      "d",
      "e",
      "c",
      "a",
      "e",
      "y",
      "e",
      "d",
      "n",
      "i",
      "s",
      "t",
      "o",
      "r",
      "i",
      "b",
      "e",
      "o",
      "o",
      "w",
      "s",
      "i",
      "t",
      "t",
      "n",
      "a",
      "e",
      "n",
      "l",
      "Spaces",
      "i",
      "t",
      "e",
      "b",
      "g",
      "n",
      "g",
      "s",
      "Spaces",
      "w",
      "x",
      "n",
      "x",
      "n",
      "a",
      "w",
      "s",
      "e",
      "e",
      "l",
      "y",
      "t",
      "v",
      "e",
      "r",
      "g",
      "n",
      "a",
      "e",
      "Spaces",
      "h",
      "t",
      "n",
      "m",
      "p",
      "p",
      "Spaces",
      "c",
      "d",
      "Spaces",
      "t",
      "e",
      "b",
      "Spaces",
      "o",
      "y",
      "t",
      "i",
      "r",
      "i",
      "r"
    ]
  },
  {
    "TestEndTime": "2021/9/3 P.M. 09:00:33",
    "TestLength": 5,
    "TotalChars": 1408,
    "GoodChars": 1321,
    "TotalBack": 64,
    "WrongWords": [
      "an",
      "people",
      "chosen",
      "mostly",
      "bread",
      "brandy",
      "him",
      "even",
      "system",
      "is",
      "area",
      "sometimes"
    ],
    "WrongChars": [
      "f",
      "e",
      "h",
      "b",
      "c",
      "n",
      "c",
      "r",
      "n",
      "e",
      "e",
      "l",
      "g",
      "n",
      "i",
      "o",
      "d",
      "i",
      "s",
      "r",
      "c",
      "p",
      "l",
      "e",
      "c",
      "g",
      "r",
      "a",
      "p",
      "w",
      "r",
      "u",
      "h",
      "y",
      "Spaces",
      "i",
      "e",
      "b",
      "x",
      "Spaces",
      "t",
      "t",
      "a",
      "Spaces",
      "s",
      "Spaces",
      "n",
      "w",
      "b",
      "b",
      "r",
      "a",
      "n",
      "d",
      "y",
      "m",
      "Spaces",
      "d",
      "f",
      "Spaces",
      "o",
      "o",
      "w",
      "e",
      "f",
      "i",
      "a",
      "v",
      "r",
      "e",
      "s",
      "b",
      "o",
      "w",
      "a",
      "u",
      "e",
      "m",
      "a",
      "s",
      "m",
      "m",
      "i",
      "a",
      "Spaces",
      "e",
      "s"
    ]
  },
  {
    "TestEndTime": "2021/9/3 P.M. 09:02:31",
    "TestLength": 1,
    "TotalChars": 316,
    "GoodChars": 303,
    "TotalBack": 13,
    "WrongWords": [],
    "WrongChars": [
      "l",
      "a",
      "a",
      "p",
      "t",
      "p",
      "r",
      "i",
      "d",
      "n",
      "i",
      "a",
      "b"
    ]
  },
  {
    "TestEndTime": "2021/9/3 P.M. 09:09:35",
    "TestLength": 1,
    "TotalChars": 303,
    "GoodChars": 286,
    "TotalBack": 12,
    "WrongWords": ["thing", "of"],
    "WrongChars": [
      "Spaces",
      "h",
      "t",
      "n",
      "g",
      "e",
      "s",
      "i",
      "Spaces",
      "Spaces",
      "t",
      "Spaces",
      "s",
      "l",
      "Spaces",
      "Spaces",
      "Spaces"
    ]
  },
  {
    "TestEndTime": "2021/9/3 P.M. 09:10:41",
    "TestLength": 1,
    "TotalChars": 312,
    "GoodChars": 291,
    "TotalBack": 16,
    "WrongWords": ["trustees"],
    "WrongChars": [
      "i",
      "s",
      "m",
      "s",
      "i",
      "i",
      "w",
      "a",
      "s",
      "s",
      "i",
      "i",
      "e",
      "f",
      "u",
      "s",
      "t",
      "e",
      "s",
      "b",
      "a"
    ]
  },
  {
    "TestEndTime": "2021/9/3 P.M. 10:42:55",
    "TestLength": 3,
    "TotalChars": 889,
    "GoodChars": 852,
    "TotalBack": 28,
    "WrongWords": ["buy", "something", "something", "the"],
    "WrongChars": [
      "u",
      "y",
      "Spaces",
      "g",
      "t",
      "i",
      "t",
      "s",
      "e",
      "Spaces",
      "e",
      "o",
      "t",
      "l",
      "d",
      "t",
      "a",
      "Spaces",
      "Spaces",
      "o",
      "r",
      "e",
      "l",
      "l",
      "s",
      "n",
      "g",
      "n",
      "g",
      "t",
      "h",
      "o",
      "c",
      "l",
      "a",
      "a",
      "f"
    ]
  },
  {
    "TestEndTime": "2021/9/5 A.M. 11:57:10",
    "TestLength": 3,
    "TotalChars": 830,
    "GoodChars": 777,
    "TotalBack": 48,
    "WrongWords": ["position", "to", "weekend"],
    "WrongChars": [
      "n",
      "Spaces",
      "g",
      "u",
      "t",
      "a",
      "t",
      "a",
      "Spaces",
      "e",
      "t",
      "t",
      "r",
      "h",
      "v",
      "l",
      "o",
      "e",
      "s",
      "i",
      "m",
      "m",
      "m",
      "i",
      "c",
      "p",
      "o",
      "o",
      "o",
      "v",
      "o",
      "r",
      "e",
      "v",
      "o",
      "l",
      "o",
      "h",
      "o",
      "p",
      "i",
      "h",
      "s",
      "g",
      "i",
      "n",
      "d",
      "f",
      "l",
      "s",
      "u",
      "f",
      "a"
    ]
  },
  {
    "TestEndTime": "2021/9/5 A.M. 11:58:44",
    "TestLength": 1,
    "TotalChars": 294,
    "GoodChars": 263,
    "TotalBack": 18,
    "WrongWords": ["girl", "around", "against", "the", "displayed"],
    "WrongChars": [
      "e",
      "s",
      "o",
      "s",
      "e",
      "n",
      "o",
      "Spaces",
      "s",
      "e",
      "n",
      "o",
      "e",
      "g",
      "r",
      "a",
      "r",
      "o",
      "u",
      "n",
      "d",
      "s",
      "a",
      "a",
      "a",
      "t",
      "h",
      "e",
      "g",
      "i",
      "k"
    ]
  },
  {
    "TestEndTime": "2021/9/5 P.M. 12:01:08",
    "TestLength": 2,
    "TotalChars": 577,
    "GoodChars": 540,
    "TotalBack": 29,
    "WrongWords": ["feeling", "pit", "decision", "from"],
    "WrongChars": [
      "g",
      "v",
      "o",
      "n",
      "g",
      "Spaces",
      "Spaces",
      "Spaces",
      "e",
      "c",
      "a",
      "m",
      "h",
      "Spaces",
      "n",
      "a",
      "l",
      "n",
      "f",
      "o",
      "v",
      "r",
      "u",
      "p",
      "t",
      "s",
      "e",
      "f",
      "s",
      "r",
      "o",
      "m",
      "i",
      "l",
      "o",
      "h",
      "a"
    ]
  },
  {
    "TestEndTime": "2021/9/5 P.M. 12:06:17",
    "TestLength": 5,
    "TotalChars": 1408,
    "GoodChars": 1304,
    "TotalBack": 84,
    "WrongWords": [
      "say",
      "since",
      "complaint",
      "our",
      "stuck",
      "each",
      "that",
      "abuser",
      "page",
      "a",
      "was"
    ],
    "WrongChars": [
      "t",
      "i",
      "a",
      "y",
      "a",
      "e",
      "Spaces",
      "t",
      "s",
      "a",
      "h",
      "n",
      "e",
      "c",
      "a",
      "a",
      "r",
      "k",
      "o",
      "c",
      "e",
      "d",
      "a",
      "e",
      "e",
      "o",
      "w",
      "Spaces",
      "o",
      "v",
      "s",
      "l",
      "p",
      "i",
      "n",
      "r",
      "e",
      "k",
      "a",
      "s",
      "a",
      "z",
      "h",
      "Spaces",
      "h",
      "i",
      "p",
      "e",
      "w",
      "e",
      "k",
      "p",
      "s",
      "Spaces",
      "n",
      "h",
      "d",
      "i",
      "t",
      "e",
      "m",
      "t",
      "h",
      "d",
      "e",
      "b",
      "l",
      "l",
      "i",
      "k",
      "l",
      "e",
      "l",
      "f",
      "l",
      "e",
      "f",
      "n",
      "o",
      "Spaces",
      "e",
      "g",
      "a",
      "Spaces",
      "p",
      "a",
      "g",
      "e",
      "w",
      "a",
      "w",
      "s",
      "a",
      "m",
      "r",
      "o",
      "e",
      "c",
      "a",
      "s",
      "a",
      "e",
      "m",
      "e"
    ]
  },
  {
    "TestEndTime": "2021/9/5 P.M. 12:11:26",
    "TestLength": 3,
    "TotalChars": 793,
    "GoodChars": 727,
    "TotalBack": 54,
    "WrongWords": ["continues", "and", "news", "subject"],
    "WrongChars": [
      "s",
      "c",
      "o",
      "n",
      "t",
      "i",
      "n",
      "u",
      "e",
      "s",
      "a",
      "c",
      "n",
      "e",
      "s",
      "Spaces",
      "y",
      "l",
      "r",
      "i",
      "i",
      "k",
      "k",
      "Spaces",
      "d",
      "n",
      "a",
      "m",
      "Spaces",
      "t",
      "r",
      "u",
      "a",
      "d",
      "o",
      "o",
      "t",
      "l",
      "a",
      "c",
      "c",
      "a",
      "Spaces",
      "Spaces",
      "e",
      "m",
      "e",
      "t",
      "o",
      "v",
      "s",
      "Spaces",
      "t",
      "b",
      "i",
      "v",
      "t",
      "a",
      "a",
      "g",
      "Spaces",
      "d",
      "e",
      "a",
      "t",
      "u"
    ]
  },
  {
    "TestEndTime": "2021/9/8 P.M. 01:31:35",
    "TestLength": 3,
    "TotalChars": 801,
    "GoodChars": 722,
    "TotalBack": 69,
    "WrongWords": ["thorn", "something", "there", "join", "have", "in"],
    "WrongChars": [
      "a",
      "r",
      "m",
      "m",
      "u",
      "n",
      "c",
      "o",
      "h",
      "s",
      "c",
      "k",
      "n",
      "Spaces",
      "Spaces",
      "k",
      "Spaces",
      "e",
      "k",
      "a",
      "e",
      "f",
      "n",
      "o",
      "r",
      "Spaces",
      "r",
      "e",
      "v",
      "u",
      "g",
      "e",
      "c",
      "g",
      "t",
      "a",
      "a",
      "g",
      "n",
      "i",
      "Spaces",
      "Spaces",
      "g",
      "n",
      "i",
      "r",
      "e",
      "i",
      "s",
      "o",
      "l",
      "l",
      "l",
      "Spaces",
      "h",
      "g",
      "o",
      "s",
      "y",
      "o",
      "r",
      "n",
      "g",
      "n",
      "a",
      "Spaces",
      "n",
      "Spaces",
      "v",
      "e",
      "t",
      "i",
      "e",
      "r",
      "t",
      "a",
      "Spaces",
      "Spaces",
      "Spaces"
    ]
  },
  {
    "TestEndTime": "2021/9/8 P.M. 01:35:17",
    "TestLength": 3,
    "TotalChars": 814,
    "GoodChars": 755,
    "TotalBack": 51,
    "WrongWords": ["thousands", "of", "becomes", "advice", "thousand"],
    "WrongChars": [
      "e",
      "m",
      "o",
      "a",
      "s",
      "e",
      "d",
      "i",
      "a",
      "a",
      "Spaces",
      "e",
      "e",
      "g",
      "a",
      "a",
      "s",
      "e",
      "g",
      "a",
      "s",
      "o",
      "w",
      "f",
      "Spaces",
      "a",
      "t",
      "t",
      "a",
      "u",
      "t",
      "i",
      "a",
      "c",
      "e",
      "s",
      "r",
      "o",
      "e",
      "e",
      "e",
      "c",
      "c",
      "e",
      "Spaces",
      "a",
      "r",
      "o",
      "r",
      "c",
      "o",
      "d",
      "z",
      "p",
      "Spaces",
      "d",
      "h",
      "h",
      "e"
    ]
  },
  {
    "TestEndTime": "2021/9/15 A.M. 12:49:10",
    "TestLength": 3,
    "TotalChars": 750,
    "GoodChars": 679,
    "TotalBack": 56,
    "WrongWords": ["determined", "was", "tongue", "by", "viewers"],
    "WrongChars": [
      "d",
      "i",
      "b",
      "Spaces",
      "d",
      "Spaces",
      "l",
      "n",
      "e",
      "n",
      "y",
      "y",
      "s",
      "a",
      "s",
      "n",
      "e",
      "n",
      "h",
      "u",
      "r",
      "o",
      "n",
      "g",
      "u",
      "e",
      "Spaces",
      "k",
      "i",
      "e",
      "o",
      "j",
      "e",
      "o",
      "l",
      "w",
      "a",
      "c",
      "s",
      "r",
      "e",
      "d",
      "u",
      "n",
      "t",
      "e",
      "e",
      "n",
      "e",
      "n",
      "s",
      "s",
      "b",
      "y",
      "l",
      "p",
      "s",
      "p",
      "e",
      "l",
      "e",
      "e",
      "t",
      "f",
      "f",
      "f",
      "b",
      "n",
      "a",
      "o",
      "y"
    ]
  },
  {
    "TestEndTime": "2021/9/15 A.M. 12:52:27",
    "TestLength": 3,
    "TotalChars": 813,
    "GoodChars": 762,
    "TotalBack": 49,
    "WrongWords": ["simulated", "making"],
    "WrongChars": [
      "d",
      "i",
      "b",
      "Spaces",
      "Spaces",
      "y",
      "e",
      "f",
      "l",
      "e",
      "Spaces",
      "e",
      "i",
      "s",
      "e",
      "o",
      "g",
      "s",
      "u",
      "a",
      "e",
      "r",
      "c",
      "Spaces",
      "m",
      "i",
      "m",
      "i",
      "h",
      "o",
      "p",
      "y",
      "h",
      "f",
      "i",
      "l",
      "b",
      "w",
      "o",
      "Spaces",
      "h",
      "t",
      "a",
      "c",
      "a",
      "h",
      "t",
      "e",
      "n",
      "a",
      "a"
    ]
  },
  {
    "TestEndTime": "2021/9/15 A.M. 12:53:37",
    "TestLength": 1,
    "TotalChars": 282,
    "GoodChars": 260,
    "TotalBack": 14,
    "WrongWords": ["activity", "a", "restless"],
    "WrongChars": [
      "r",
      "e",
      "t",
      "y",
      "o",
      "Spaces",
      "Spaces",
      "Spaces",
      "i",
      "w",
      "t",
      "o",
      "a",
      "o",
      "p",
      "t",
      "l",
      "e",
      "s",
      "s",
      "p",
      "a"
    ]
  },
  {
    "TestEndTime": "2021/9/15 A.M. 12:57:05",
    "TestLength": 3,
    "TotalChars": 860,
    "GoodChars": 816,
    "TotalBack": 31,
    "WrongWords": [
      "work",
      "beauty",
      "that",
      "police",
      "that",
      "other",
      "with",
      "slant"
    ],
    "WrongChars": [
      "k",
      "g",
      "Spaces",
      "t",
      "a",
      "u",
      "u",
      "y",
      "t",
      "e",
      "e",
      "n",
      "o",
      "Spaces",
      "v",
      "b",
      "y",
      "t",
      "u",
      "u",
      "t",
      "h",
      "v",
      "e",
      "b",
      "c",
      "a",
      "Spaces",
      "h",
      "a",
      "t",
      "e",
      "k",
      "o",
      "o",
      "s",
      "a",
      "Spaces",
      "u",
      "s",
      "r",
      "w",
      "i",
      "s"
    ]
  },
  {
    "TestEndTime": "2021/9/15 A.M. 01:00:21",
    "TestLength": 3,
    "TotalChars": 846,
    "GoodChars": 797,
    "TotalBack": 34,
    "WrongWords": [
      "thinks",
      "that",
      "sometimes",
      "by",
      "aphids",
      "wings",
      "and",
      "about",
      "rudely"
    ],
    "WrongChars": [
      "s",
      "k",
      "k",
      "s",
      "Spaces",
      "k",
      "c",
      "v",
      "i",
      "t",
      "o",
      "Spaces",
      "e",
      "t",
      "s",
      "Spaces",
      "l",
      "i",
      "k",
      "v",
      "i",
      "e",
      "s",
      "t",
      "h",
      "Spaces",
      "e",
      "s",
      "b",
      "y",
      "a",
      "p",
      "r",
      "p",
      "d",
      "i",
      "a",
      "g",
      "n",
      "d",
      "i",
      "k",
      "l",
      "t",
      "g",
      "Spaces",
      "r",
      "l",
      "y"
    ]
  },
  {
    "TestEndTime": "2021/9/15 A.M. 01:10:23",
    "TestLength": 2,
    "TotalChars": 515,
    "GoodChars": 457,
    "TotalBack": 31,
    "WrongWords": [
      "the",
      "of",
      "or",
      "unhinge",
      "separate",
      "been",
      "synthesized",
      "a",
      "that",
      "it",
      "would"
    ],
    "WrongChars": [
      "a",
      "t",
      "h",
      "r",
      "c",
      "o",
      "f",
      "s",
      "a",
      "o",
      "o",
      "w",
      "o",
      "r",
      "Spaces",
      "c",
      "s",
      "h",
      "Spaces",
      "e",
      "h",
      "e",
      "o",
      "t",
      "e",
      "e",
      "d",
      "n",
      "o",
      "a",
      "r",
      "a",
      "t",
      "e",
      "u",
      "t",
      "n",
      "s",
      "y",
      "n",
      "i",
      "a",
      "a",
      "r",
      "e",
      "r",
      "t",
      "h",
      "o",
      "e",
      "i",
      "i",
      "t",
      "w",
      "o",
      "u",
      "l",
      "d"
    ]
  },
  {
    "TestEndTime": "2021/9/15 P.M. 01:47:41",
    "TestLength": 3,
    "TotalChars": 866,
    "GoodChars": 812,
    "TotalBack": 41,
    "WrongWords": [
      "on",
      "conjugate",
      "on",
      "that",
      "something",
      "people",
      "one",
      "by"
    ],
    "WrongChars": [
      "a",
      "i",
      "o",
      "n",
      "u",
      "n",
      "p",
      "y",
      "h",
      "t",
      "m",
      "e",
      "e",
      "h",
      "t",
      "a",
      "n",
      "a",
      "t",
      "Spaces",
      "e",
      "o",
      "s",
      "n",
      "e",
      "i",
      "x",
      "d",
      "e",
      "t",
      "e",
      "y",
      "e",
      "g",
      "g",
      "i",
      "n",
      "h",
      "t",
      "i",
      "r",
      "Spaces",
      "e",
      "t",
      "t",
      "n",
      "b",
      "y",
      "a",
      "t",
      "d",
      "r",
      "a",
      "m"
    ]
  },
  {
    "TestEndTime": "2021/9/15 P.M. 03:34:16",
    "TestLength": 2,
    "TotalChars": 596,
    "GoodChars": 572,
    "TotalBack": 19,
    "WrongWords": ["some", "a", "may", "mechanical"],
    "WrongChars": [
      "m",
      "e",
      "g",
      "l",
      "o",
      "h",
      "w",
      "e",
      "l",
      "a",
      "u",
      "Spaces",
      "Spaces",
      "e",
      "r",
      "y",
      "l",
      "e",
      "e",
      "l",
      "l",
      "o",
      "r",
      "e"
    ]
  },
  {
    "TestEndTime": "2021/9/15 P.M. 03:39:23",
    "TestLength": 3,
    "TotalChars": 921,
    "GoodChars": 878,
    "TotalBack": 29,
    "WrongWords": [
      "wall",
      "of",
      "bad",
      "off",
      "stomach",
      "something",
      "someone"
    ],
    "WrongChars": [
      "b",
      "e",
      "d",
      "d",
      "a",
      "l",
      "l",
      "o",
      "f",
      "a",
      "Spaces",
      "a",
      "s",
      "a",
      "z",
      "o",
      "o",
      "x",
      "f",
      "a",
      "g",
      "n",
      "Spaces",
      "r",
      "s",
      "h",
      "h",
      "l",
      "a",
      "r",
      "n",
      "g",
      "p",
      "r",
      "p",
      "p",
      "m",
      "e",
      "o",
      "n",
      "e",
      "Spaces",
      "s"
    ]
  },
  {
    "TestEndTime": "2021/9/15 P.M. 03:52:38",
    "TestLength": 1,
    "TotalChars": 284,
    "GoodChars": 264,
    "TotalBack": 20,
    "WrongWords": [],
    "WrongChars": [
      "s",
      "a",
      "m",
      "e",
      "o",
      "r",
      "a",
      "t",
      "a",
      "s",
      "i",
      "m",
      "c",
      "r",
      "u",
      "h",
      "a",
      "u",
      "e",
      "s"
    ]
  },
  {
    "TestEndTime": "2021/9/15 P.M. 03:53:56",
    "TestLength": 1,
    "TotalChars": 316,
    "GoodChars": 303,
    "TotalBack": 7,
    "WrongWords": ["difficult", "or", "elements", "try", "to"],
    "WrongChars": [
      "t",
      "r",
      "i",
      "f",
      "o",
      "a",
      "e",
      "h",
      "n",
      "t",
      "a",
      "Spaces",
      "o"
    ]
  },
  {
    "TestEndTime": "2021/9/15 P.M. 03:57:33",
    "TestLength": 3,
    "TotalChars": 894,
    "GoodChars": 834,
    "TotalBack": 40,
    "WrongWords": [
      "reputation",
      "reputation",
      "that",
      "a",
      "something",
      "while",
      "government"
    ],
    "WrongChars": [
      "s",
      "r",
      "e",
      "p",
      "n",
      "Spaces",
      "t",
      "u",
      "a",
      "t",
      "i",
      "o",
      "n",
      "Spaces",
      "t",
      "h",
      "a",
      "c",
      "a",
      "t",
      "c",
      "c",
      "o",
      "a",
      "e",
      "v",
      "r",
      "o",
      "w",
      "o",
      "m",
      "s",
      "a",
      "p",
      "s",
      "Spaces",
      "p",
      "a",
      "u",
      "c",
      "n",
      "e",
      "n",
      "g",
      "w",
      "w",
      "h",
      "d",
      "n",
      "m",
      "e",
      "n",
      "t",
      "o",
      "x",
      "g",
      "d",
      "u",
      "r",
      "s"
    ]
  },
  {
    "TestEndTime": "2021/9/15 P.M. 04:01:32",
    "TestLength": 2,
    "TotalChars": 558,
    "GoodChars": 523,
    "TotalBack": 31,
    "WrongWords": ["sinister", "campaigner", "shot", "a"],
    "WrongChars": [
      "Spaces",
      "o",
      "e",
      "Spaces",
      "t",
      "c",
      "i",
      "i",
      "a",
      "e",
      "n",
      "t",
      "s",
      "i",
      "p",
      "a",
      "e",
      "a",
      "g",
      "a",
      "o",
      "w",
      "t",
      "r",
      "u",
      "l",
      "b",
      "Spaces",
      "e",
      "l",
      "a",
      "e",
      "i",
      "d",
      "e"
    ]
  },
  {
    "TestEndTime": "2021/9/15 P.M. 04:06:31",
    "TestLength": 3,
    "TotalChars": 933,
    "GoodChars": 899,
    "TotalBack": 29,
    "WrongWords": ["to", "feeling"],
    "WrongChars": [
      "t",
      "s",
      "r",
      "e",
      "f",
      "u",
      "s",
      "e",
      "t",
      "Spaces",
      "b",
      "i",
      "p",
      "o",
      "t",
      "o",
      "Spaces",
      "n",
      "g",
      "n",
      "u",
      "o",
      "r",
      "a",
      "b",
      "c",
      "h",
      "t",
      "i",
      "e",
      "u",
      "o",
      "r",
      "d"
    ]
  },
  {
    "TestEndTime": "2021/9/15 P.M. 04:14:36",
    "TestLength": 1,
    "TotalChars": 326,
    "GoodChars": 312,
    "TotalBack": 8,
    "WrongWords": ["him", "be"],
    "WrongChars": [
      "h",
      "i",
      "m",
      "Spaces",
      "x",
      "p",
      "o",
      "e",
      "p",
      "v",
      "e",
      "b",
      "e",
      "e"
    ]
  },
  {
    "TestEndTime": "2021/9/15 P.M. 04:23:07",
    "TestLength": 1,
    "TotalChars": 316,
    "GoodChars": 306,
    "TotalBack": 9,
    "WrongWords": ["or"],
    "WrongChars": ["i", "l", "i", "d", "r", "r", "o", "f", "i", "r"]
  },
  {
    "TestEndTime": "2021/9/15 P.M. 04:33:29",
    "TestLength": 1,
    "TotalChars": 303,
    "GoodChars": 284,
    "TotalBack": 14,
    "WrongWords": ["to", "something", "amounts"],
    "WrongChars": [
      "g",
      "n",
      "c",
      "t",
      "o",
      "a",
      "d",
      "o",
      "o",
      "Spaces",
      "n",
      "o",
      "s",
      "o",
      "t",
      "c",
      "n",
      "g",
      "s"
    ]
  },
  {
    "TestEndTime": "2021/9/16 A.M. 01:18:15",
    "TestLength": 1,
    "TotalChars": 263,
    "GoodChars": 248,
    "TotalBack": 14,
    "WrongWords": ["synthesized"],
    "WrongChars": [
      "z",
      "n",
      "a",
      "d",
      "e",
      "e",
      "n",
      "o",
      "s",
      "p",
      "n",
      "i",
      "n",
      "n",
      "e"
    ]
  },
  {
    "TestEndTime": "2021/9/16 P.M. 01:53:35",
    "TestLength": 1,
    "TotalChars": 292,
    "GoodChars": 267,
    "TotalBack": 23,
    "WrongWords": ["bellwither", "an"],
    "WrongChars": [
      "l",
      "u",
      "d",
      "c",
      "n",
      "b",
      "b",
      "r",
      "Spaces",
      "i",
      "m",
      "o",
      "n",
      "e",
      "Spaces",
      "v",
      "v",
      "k",
      "a",
      "g",
      "n",
      "r",
      "g",
      "i",
      "a"
    ]
  },
  {
    "TestEndTime": "2021/9/16 P.M. 02:37:50",
    "TestLength": 1,
    "TotalChars": 318,
    "GoodChars": 301,
    "TotalBack": 7,
    "WrongWords": ["slaves", "usually", "difficulties"],
    "WrongChars": [
      "Spaces",
      "i",
      "l",
      "a",
      "v",
      "e",
      "s",
      "Spaces",
      "r",
      "y",
      "Spaces",
      "l",
      "t",
      "o",
      "n",
      "a",
      "w"
    ]
  },
  {
    "TestEndTime": "2021/9/16 P.M. 05:50:17",
    "TestLength": 3,
    "TotalChars": 889,
    "GoodChars": 850,
    "TotalBack": 28,
    "WrongWords": ["nonentity", "unusual", "bag", "peanuts", "exists", "some"],
    "WrongChars": [
      "c",
      "n",
      "t",
      "i",
      "t",
      "y",
      "Spaces",
      "p",
      "t",
      "n",
      "e",
      "b",
      "a",
      "h",
      "r",
      "o",
      "Spaces",
      "g",
      "u",
      "s",
      "s",
      "e",
      "j",
      "u",
      "s",
      "t",
      "e",
      "h",
      "t",
      "s",
      "o",
      "Spaces",
      "m",
      "z",
      "a",
      "a",
      "Spaces",
      "m",
      "u"
    ]
  },
  {
    "TestEndTime": "2021/9/16 P.M. 05:59:56",
    "TestLength": 5,
    "TotalChars": 1511,
    "GoodChars": 1438,
    "TotalBack": 58,
    "WrongWords": [
      "are",
      "small",
      "circle",
      "computer",
      "humiliating",
      "them",
      "that",
      "flooding"
    ],
    "WrongChars": [
      "c",
      "Spaces",
      "x",
      "a",
      "e",
      "t",
      "l",
      "t",
      "u",
      "b",
      "r",
      "o",
      "a",
      "h",
      "t",
      "l",
      "l",
      "i",
      "r",
      "e",
      "l",
      "c",
      "l",
      "e",
      "Spaces",
      "d",
      "Spaces",
      "r",
      "e",
      "e",
      "r",
      "g",
      "a",
      "g",
      "n",
      "i",
      "Spaces",
      "h",
      "t",
      "m",
      "a",
      "a",
      "l",
      "u",
      "l",
      "u",
      "c",
      "t",
      "h",
      "r",
      "i",
      "n",
      "g",
      "Spaces",
      "o",
      "l",
      "e",
      "u",
      "o",
      "e",
      "h",
      "w",
      "m",
      "a",
      "m",
      "m",
      "s",
      "t",
      "p",
      "n",
      "e",
      "g",
      "a"
    ]
  },
  {
    "TestEndTime": "2021/9/17 P.M. 10:18:19",
    "TestLength": 1,
    "TotalChars": 279,
    "GoodChars": 275,
    "TotalBack": 4,
    "WrongWords": [],
    "WrongChars": ["w", "e", "o", "Spaces"]
  },
  {
    "TestEndTime": "2021/9/20 P.M. 04:06:09",
    "TestLength": 1,
    "TotalChars": 278,
    "GoodChars": 257,
    "TotalBack": 14,
    "WrongWords": ["something"],
    "WrongChars": [
      "s",
      "e",
      "t",
      "h",
      "i",
      "n",
      "g",
      "v",
      "l",
      "o",
      "h",
      "t",
      "n",
      "i",
      "s",
      "a",
      "s",
      "o",
      "r",
      "a",
      "s"
    ]
  },
  {
    "TestEndTime": "2021/9/20 P.M. 04:07:36",
    "TestLength": 1,
    "TotalChars": 266,
    "GoodChars": 252,
    "TotalBack": 8,
    "WrongWords": ["smuggle", "in"],
    "WrongChars": [
      "g",
      "g",
      "e",
      "h",
      "e",
      "h",
      "e",
      "h",
      "e",
      "n",
      "Spaces",
      "s",
      "t",
      "o"
    ]
  },
  {
    "TestEndTime": "2021/9/20 P.M. 08:21:35",
    "TestLength": 5,
    "TotalChars": 1418,
    "GoodChars": 1335,
    "TotalBack": 56,
    "WrongWords": [
      "itchy",
      "something",
      "metals",
      "trying",
      "object",
      "mood",
      "off",
      "something",
      "for",
      "cocaine",
      "intention"
    ],
    "WrongChars": [
      "y",
      "s",
      "r",
      "t",
      "e",
      "p",
      "e",
      "r",
      "s",
      "o",
      "a",
      "l",
      "j",
      "e",
      "Spaces",
      "n",
      "g",
      "h",
      "g",
      "e",
      "r",
      "t",
      "i",
      "n",
      "g",
      "Spaces",
      "b",
      "Spaces",
      "t",
      "t",
      "c",
      "e",
      "e",
      "c",
      "t",
      "e",
      "l",
      "a",
      "o",
      "d",
      "f",
      "a",
      "s",
      "p",
      "n",
      "g",
      "l",
      "b",
      "f",
      "o",
      "l",
      "y",
      "e",
      "s",
      "d",
      "y",
      "h",
      "g",
      "n",
      "n",
      "l",
      "a",
      "e",
      "h",
      "e",
      "Spaces",
      "e",
      "Spaces",
      "r",
      "o",
      "f",
      "f",
      "c",
      "t",
      "a",
      "t",
      "t",
      "e",
      "n",
      "t",
      "i",
      "o",
      "n"
    ]
  },
  {
    "TestEndTime": "2021/9/20 P.M. 08:27:24",
    "TestLength": 5,
    "TotalChars": 1457,
    "GoodChars": 1386,
    "TotalBack": 58,
    "WrongWords": [
      "that",
      "by",
      "sending",
      "that",
      "do",
      "as",
      "something",
      "revealing"
    ],
    "WrongChars": [
      "a",
      "a",
      "t",
      "r",
      "Spaces",
      "s",
      "v",
      "e",
      "h",
      "b",
      "n",
      "g",
      "s",
      "e",
      "a",
      "a",
      "r",
      "r",
      "a",
      "r",
      "e",
      "p",
      "u",
      "x",
      "a",
      "t",
      "Spaces",
      "e",
      "n",
      "o",
      "d",
      "e",
      "s",
      "t",
      "a",
      "s",
      "Spaces",
      "h",
      "e",
      "w",
      "t",
      "a",
      "b",
      "u",
      "s",
      "v",
      "w",
      "e",
      "l",
      "s",
      "Spaces",
      "a",
      "Spaces",
      "Spaces",
      "n",
      "g",
      "a",
      "Spaces",
      "g",
      "n",
      "i",
      "n",
      "g",
      "r",
      "e",
      "h",
      "a",
      "Spaces",
      "s",
      "Spaces",
      "r"
    ]
  },
  {
    "TestEndTime": "2021/9/20 P.M. 08:34:03",
    "TestLength": 6,
    "TotalChars": 1672,
    "GoodChars": 1565,
    "TotalBack": 85,
    "WrongWords": [
      "the",
      "thinking",
      "of",
      "a",
      "new",
      "something",
      "made",
      "in",
      "working",
      "environmental",
      "to",
      "intructions",
      "offer"
    ],
    "WrongChars": [
      "a",
      "h",
      "Spaces",
      "n",
      "c",
      "Spaces",
      "w",
      "o",
      "c",
      "y",
      "l",
      "t",
      "n",
      "n",
      "t",
      "a",
      "i",
      "Spaces",
      "l",
      "i",
      "l",
      "n",
      "o",
      "o",
      "f",
      "a",
      "Spaces",
      "n",
      "e",
      "w",
      "s",
      "u",
      "m",
      "e",
      "n",
      "g",
      "n",
      "Spaces",
      "i",
      "n",
      "l",
      "Spaces",
      "a",
      "Spaces",
      "d",
      "o",
      "l",
      "w",
      "e",
      "c",
      "n",
      "e",
      "i",
      "l",
      "g",
      "e",
      "a",
      "e",
      "n",
      "g",
      "a",
      "o",
      "v",
      "n",
      "o",
      "r",
      "f",
      "i",
      "a",
      "s",
      "r",
      "o",
      "c",
      "o",
      "e",
      "i",
      "t",
      "r",
      "e",
      "e",
      "e",
      "v",
      "v",
      "r",
      "e",
      "c",
      "u",
      "t",
      "z",
      "n",
      "r",
      "Spaces",
      "n",
      "b",
      "a",
      "h",
      "h",
      "t",
      "s",
      "t",
      "c",
      "i",
      "Spaces",
      "t",
      "c",
      "s",
      "Spaces"
    ]
  },
  {
    "TestEndTime": "2021/9/20 P.M. 08:36:04",
    "TestLength": 1,
    "TotalChars": 307,
    "GoodChars": 299,
    "TotalBack": 6,
    "WrongWords": [],
    "WrongChars": ["g", "a", "e", "e", "e", "n", "c", "a"]
  },
  {
    "TestEndTime": "2021/9/20 P.M. 08:39:12",
    "TestLength": 2,
    "TotalChars": 560,
    "GoodChars": 535,
    "TotalBack": 24,
    "WrongWords": ["as"],
    "WrongChars": [
      "o",
      "u",
      "o",
      "z",
      "e",
      "c",
      "a",
      "e",
      "s",
      "e",
      "e",
      "n",
      "o",
      "w",
      "s",
      "a",
      "h",
      "t",
      "s",
      "a",
      "t",
      "i",
      "t",
      "d",
      "b"
    ]
  },
  {
    "TestEndTime": "2021/9/20 P.M. 08:40:22",
    "TestLength": 1,
    "TotalChars": 277,
    "GoodChars": 260,
    "TotalBack": 15,
    "WrongWords": ["compound", "the"],
    "WrongChars": [
      "e",
      "t",
      "e",
      "r",
      "r",
      "Spaces",
      "a",
      "d",
      "f",
      "s",
      "u",
      "i",
      "t",
      "n",
      "i",
      "s",
      "Spaces"
    ]
  },
  {
    "TestEndTime": "2021/9/20 P.M. 08:47:49",
    "TestLength": 7,
    "TotalChars": 1865,
    "GoodChars": 1748,
    "TotalBack": 92,
    "WrongWords": [
      "reversible",
      "assault",
      "sudden",
      "inference",
      "the",
      "govenment",
      "her",
      "in",
      "is",
      "other",
      "do",
      "something"
    ],
    "WrongChars": [
      "p",
      "p",
      "r",
      "Spaces",
      "t",
      "e",
      "r",
      "l",
      "e",
      "o",
      "Spaces",
      "g",
      "e",
      "n",
      "u",
      "i",
      "m",
      "e",
      "e",
      "f",
      "n",
      "a",
      "c",
      "l",
      "c",
      "a",
      "u",
      "t",
      "Spaces",
      "n",
      "c",
      "e",
      "n",
      "i",
      "Spaces",
      "e",
      "n",
      "o",
      "a",
      "t",
      "h",
      "e",
      "n",
      "e",
      "n",
      "m",
      "e",
      "n",
      "t",
      "Spaces",
      "p",
      "e",
      "t",
      "o",
      "h",
      "t",
      "i",
      "Spaces",
      "h",
      "b",
      "g",
      "n",
      "i",
      "e",
      "b",
      "i",
      "Spaces",
      "s",
      "e",
      "i",
      "s",
      "v",
      "x",
      "i",
      "Spaces",
      "Spaces",
      "n",
      "Spaces",
      "s",
      "f",
      "d",
      "n",
      "i",
      "i",
      "l",
      "Spaces",
      "e",
      "o",
      "w",
      "m",
      "n",
      "Spaces",
      "n",
      "e",
      "s",
      "o",
      "h",
      "z",
      "e",
      "h",
      "c",
      "Spaces",
      "a",
      "p",
      "p",
      "o",
      "w",
      "t",
      "i",
      "s",
      "Spaces",
      "a",
      "n",
      "g",
      "Spaces",
      "n",
      "e"
    ]
  },
  {
    "TestEndTime": "2021/9/20 P.M. 08:53:45",
    "TestLength": 1,
    "TotalChars": 272,
    "GoodChars": 250,
    "TotalBack": 16,
    "WrongWords": ["as", "medicinal", "outside"],
    "WrongChars": [
      "s",
      "o",
      "r",
      "b",
      "Spaces",
      "k",
      "c",
      "Spaces",
      "t",
      "r",
      "o",
      "s",
      "o",
      "o",
      "s",
      "i",
      "d",
      "e",
      "i",
      "g",
      "i",
      "e"
    ]
  },
  {
    "TestEndTime": "2021/9/21 P.M. 02:07:27",
    "TestLength": 1,
    "TotalChars": 280,
    "GoodChars": 260,
    "TotalBack": 15,
    "WrongWords": ["monetary"],
    "WrongChars": [
      "i",
      "Spaces",
      "g",
      "n",
      "Spaces",
      "g",
      "e",
      "Spaces",
      "n",
      "n",
      "o",
      "t",
      "a",
      "r",
      "y",
      "Spaces",
      "a",
      "s",
      "p",
      "u"
    ]
  },
  {
    "TestEndTime": "2021/9/21 P.M. 02:08:39",
    "TestLength": 1,
    "TotalChars": 277,
    "GoodChars": 254,
    "TotalBack": 21,
    "WrongWords": ["have"],
    "WrongChars": [
      "l",
      "Spaces",
      "n",
      "i",
      "h",
      "t",
      "i",
      "s",
      "e",
      "m",
      "o",
      "e",
      "v",
      "e",
      "Spaces",
      "f",
      "a",
      "h",
      "r",
      "i",
      "a",
      "h",
      "m"
    ]
  },
  {
    "TestEndTime": "2021/9/21 P.M. 02:12:45",
    "TestLength": 3,
    "TotalChars": 859,
    "GoodChars": 817,
    "TotalBack": 30,
    "WrongWords": ["something", "consume", "macro", "that", "the"],
    "WrongChars": [
      "b",
      "o",
      "m",
      "a",
      "Spaces",
      "Spaces",
      "h",
      "s",
      "m",
      "e",
      "u",
      "g",
      "n",
      "a",
      "h",
      "x",
      "g",
      "r",
      "d",
      "r",
      "p",
      "r",
      "i",
      "d",
      "r",
      "n",
      "v",
      "a",
      "a",
      "n",
      "s",
      "a",
      "i",
      "h",
      "a",
      "t",
      "Spaces",
      "g",
      "t",
      "h",
      "e",
      "d"
    ]
  },
  {
    "TestEndTime": "2021/9/21 P.M. 02:53:34",
    "TestLength": 1,
    "TotalChars": 301,
    "GoodChars": 288,
    "TotalBack": 8,
    "WrongWords": ["an", "avert", "on", "making"],
    "WrongChars": [
      "a",
      "n",
      "e",
      "i",
      "a",
      "c",
      "Spaces",
      "s",
      "o",
      "o",
      "n",
      "a",
      "Spaces"
    ]
  },
  {
    "TestEndTime": "2021/9/21 P.M. 03:21:56",
    "TestLength": 3,
    "TotalChars": 887,
    "GoodChars": 842,
    "TotalBack": 38,
    "WrongWords": ["romans", "people", "organization", "characteristic", "say"],
    "WrongChars": [
      "s",
      "g",
      "m",
      "t",
      "s",
      "e",
      "d",
      "o",
      "o",
      "t",
      "d",
      "b",
      "p",
      "l",
      "e",
      "z",
      "n",
      "a",
      "n",
      "a",
      "s",
      "o",
      "Spaces",
      "k",
      "Spaces",
      "e",
      "c",
      "i",
      "i",
      "t",
      "p",
      "s",
      "Spaces",
      "o",
      "l",
      "h",
      "w",
      "o",
      "t",
      "i",
      "t",
      "f",
      "u",
      "r",
      "k"
    ]
  },
  {
    "TestEndTime": "2021/9/22 P.M. 11:31:06",
    "TestLength": 2,
    "TotalChars": 530,
    "GoodChars": 463,
    "TotalBack": 48,
    "WrongWords": [
      "impartial",
      "big",
      "cities",
      "when",
      "showing",
      "dining",
      "the",
      "efforts"
    ],
    "WrongChars": [
      "p",
      "o",
      "e",
      "r",
      "e",
      "a",
      "Spaces",
      "a",
      "a",
      "e",
      "a",
      "i",
      "b",
      "Spaces",
      "g",
      "i",
      "e",
      "i",
      "t",
      "i",
      "e",
      "s",
      "Spaces",
      "w",
      "h",
      "e",
      "n",
      "n",
      "g",
      "r",
      "a",
      "p",
      "m",
      "a",
      "h",
      "t",
      "i",
      "g",
      "e",
      "x",
      "o",
      "r",
      "c",
      "t",
      "i",
      "t",
      "h",
      "t",
      "t",
      "e",
      "e",
      "e",
      "e",
      "Spaces",
      "t",
      "t",
      "a",
      "t",
      "e",
      "s",
      "n",
      "n",
      "o",
      "a",
      "s",
      "s",
      "e"
    ]
  },
  {
    "TestEndTime": "2021/9/22 P.M. 11:36:07",
    "TestLength": 1,
    "TotalChars": 273,
    "GoodChars": 245,
    "TotalBack": 21,
    "WrongWords": ["packaging", "altogether", "what", "bad", "components"],
    "WrongChars": [
      "k",
      "g",
      "b",
      "r",
      "e",
      "e",
      "e",
      "t",
      "o",
      "o",
      "e",
      "s",
      "o",
      "n",
      "k",
      "Spaces",
      "t",
      "a",
      "d",
      "s",
      "a",
      "w",
      "s",
      "s",
      "a",
      "m",
      "a",
      "m"
    ]
  },
  {
    "TestEndTime": "2021/9/22 P.M. 11:38:05",
    "TestLength": 1,
    "TotalChars": 241,
    "GoodChars": 215,
    "TotalBack": 19,
    "WrongWords": ["amount", "two", "back"],
    "WrongChars": [
      "m",
      "o",
      "u",
      "n",
      "t",
      "f",
      "o",
      "e",
      "t",
      "u",
      "u",
      "t",
      "c",
      "n",
      "s",
      "a",
      "l",
      "e",
      "y",
      "Spaces",
      "k",
      "k",
      "m",
      "i",
      "b",
      "d"
    ]
  },
  {
    "TestEndTime": "2021/9/22 P.M. 11:39:18",
    "TestLength": 1,
    "TotalChars": 261,
    "GoodChars": 238,
    "TotalBack": 19,
    "WrongWords": ["an", "a", "juvenile"],
    "WrongChars": [
      "i",
      "d",
      "a",
      "n",
      "h",
      "h",
      "c",
      "f",
      "l",
      "u",
      "a",
      "a",
      "l",
      "p",
      "a",
      "a",
      "n",
      "t",
      "l",
      "i",
      "w",
      "o",
      "s"
    ]
  },
  {
    "TestEndTime": "2021/9/22 P.M. 11:40:54",
    "TestLength": 1,
    "TotalChars": 263,
    "GoodChars": 240,
    "TotalBack": 16,
    "WrongWords": ["money", "disposal", "lot", "and"],
    "WrongChars": [
      "o",
      "e",
      "s",
      "p",
      "s",
      "i",
      "d",
      "a",
      "l",
      "Spaces",
      "r",
      "i",
      "w",
      "t",
      "e",
      "r",
      "d",
      "w",
      "u",
      "a",
      "h",
      "c",
      "a"
    ]
  },
  {
    "TestEndTime": "2021/9/22 P.M. 11:43:19",
    "TestLength": 2,
    "TotalChars": 540,
    "GoodChars": 501,
    "TotalBack": 34,
    "WrongWords": ["sleep"],
    "WrongChars": [
      "v",
      "b",
      "s",
      "l",
      "e",
      "e",
      "p",
      "t",
      "i",
      "i",
      "t",
      "i",
      "e",
      "s",
      "q",
      "l",
      "p",
      "e",
      "c",
      "w",
      "a",
      "w",
      "u",
      "o",
      "r",
      "s",
      "t",
      "s",
      "i",
      "Spaces",
      "Spaces",
      "y",
      "o",
      "f",
      "v",
      "o",
      "e",
      "s",
      "u"
    ]
  },
  {
    "TestEndTime": "2021/9/23 P.M. 04:44:43",
    "TestLength": 2,
    "TotalChars": 566,
    "GoodChars": 536,
    "TotalBack": 25,
    "WrongWords": ["elected", "of", "handle"],
    "WrongChars": [
      "s",
      "c",
      "g",
      "u",
      "g",
      "Spaces",
      "o",
      "g",
      "n",
      "i",
      "y",
      "t",
      "i",
      "t",
      "t",
      "Spaces",
      "r",
      "e",
      "o",
      "f",
      "r",
      "p",
      "y",
      "Spaces",
      "s",
      "e",
      "l",
      "l",
      "e",
      "a"
    ]
  },
  {
    "TestEndTime": "2021/9/23 P.M. 04:49:50",
    "TestLength": 5,
    "TotalChars": 1431,
    "GoodChars": 1331,
    "TotalBack": 80,
    "WrongWords": [
      "because",
      "bellwether",
      "govenment",
      "guilty",
      "like",
      "event"
    ],
    "WrongChars": [
      "a",
      "u",
      "s",
      "e",
      "v",
      "e",
      "n",
      "a",
      "m",
      "o",
      "i",
      "u",
      "r",
      "f",
      "r",
      "a",
      "i",
      "o",
      "w",
      "Spaces",
      "a",
      "a",
      "d",
      "s",
      "i",
      "n",
      "w",
      "e",
      "t",
      "h",
      "e",
      "r",
      "o",
      "g",
      "n",
      "g",
      "t",
      "y",
      "Spaces",
      "g",
      "t",
      "l",
      "a",
      "o",
      "i",
      "t",
      "r",
      "Spaces",
      "Spaces",
      "Spaces",
      "e",
      "Spaces",
      "w",
      "k",
      "e",
      "n",
      "t",
      "Spaces",
      "l",
      "o",
      "p",
      "Spaces",
      "s",
      "a",
      "s",
      "t",
      "c",
      "c",
      "a",
      "e",
      "e",
      "d",
      "t",
      "y",
      "t",
      "Spaces",
      "y",
      "l",
      "o",
      "l",
      "s",
      "u",
      "o",
      "c",
      "m",
      "a",
      "m",
      "g",
      "o",
      "u",
      "h",
      "s",
      "e",
      "k",
      "s",
      "s",
      "n",
      "i",
      "b",
      "e"
    ]
  },
  {
    "TestEndTime": "2021/9/23 P.M. 04:58:18",
    "TestLength": 5,
    "TotalChars": 1472,
    "GoodChars": 1409,
    "TotalBack": 57,
    "WrongWords": ["beyond", "of", "and", "something", "reserve"],
    "WrongChars": [
      "b",
      "d",
      "e",
      "s",
      "b",
      "n",
      "p",
      "m",
      "o",
      "s",
      "b",
      "c",
      "f",
      "a",
      "d",
      "g",
      "o",
      "v",
      "e",
      "o",
      "a",
      "r",
      "e",
      "t",
      "e",
      "m",
      "t",
      "e",
      "s",
      "s",
      "s",
      "u",
      "e",
      "e",
      "a",
      "b",
      "y",
      "n",
      "u",
      "a",
      "s",
      "d",
      "r",
      "n",
      "g",
      "g",
      "c",
      "Spaces",
      "b",
      "i",
      "y",
      "e",
      "b",
      "t",
      "Spaces",
      "d",
      "z",
      "s",
      "n",
      "o",
      "c",
      "r",
      "e"
    ]
  },
  {
    "TestEndTime": "2021/9/23 P.M. 05:07:09",
    "TestLength": 3,
    "TotalChars": 861,
    "GoodChars": 791,
    "TotalBack": 53,
    "WrongWords": [
      "as",
      "over",
      "example",
      "th",
      "street",
      "thorn",
      "him",
      "my",
      "poppy"
    ],
    "WrongChars": [
      "j",
      "s",
      "i",
      "s",
      "w",
      "w",
      "k",
      "e",
      "Spaces",
      "Spaces",
      "Spaces",
      "Spaces",
      "Spaces",
      "Spaces",
      "a",
      "h",
      "a",
      "r",
      "c",
      "a",
      "h",
      "h",
      "c",
      "l",
      "e",
      "l",
      "a",
      "n",
      "i",
      "t",
      "c",
      "a",
      "s",
      "Spaces",
      "r",
      "r",
      "e",
      "t",
      "h",
      "o",
      "r",
      "m",
      "i",
      "h",
      "h",
      "m",
      "Spaces",
      "a",
      "r",
      "i",
      "a",
      "l",
      "a",
      "u",
      "s",
      "c",
      "v",
      "i",
      "d",
      "Spaces",
      "g",
      "n",
      "i",
      "l",
      "l",
      "i",
      "e",
      "Spaces",
      "a",
      "Spaces"
    ]
  },
  {
    "TestEndTime": "2021/9/23 P.M. 05:08:28",
    "TestLength": 1,
    "TotalChars": 287,
    "GoodChars": 267,
    "TotalBack": 14,
    "WrongWords": ["malaria", "quantity", "amicable", "hard"],
    "WrongChars": [
      "a",
      "Spaces",
      "h",
      "Spaces",
      "Spaces",
      "n",
      "a",
      "c",
      "o",
      "t",
      "r",
      "a",
      "p",
      "b",
      "l",
      "e",
      "a",
      "r",
      "d",
      "p"
    ]
  },
  {
    "TestEndTime": "2021/9/23 P.M. 05:09:39",
    "TestLength": 1,
    "TotalChars": 283,
    "GoodChars": 256,
    "TotalBack": 20,
    "WrongWords": ["beverages", "trench"],
    "WrongChars": [
      "v",
      "a",
      "l",
      "a",
      "Spaces",
      "a",
      "e",
      "h",
      "m",
      "e",
      "e",
      "e",
      "a",
      "n",
      "i",
      "s",
      "e",
      "r",
      "f",
      "c",
      "r",
      "r",
      "e",
      "n",
      "c",
      "h",
      "Spaces"
    ]
  },
  {
    "TestEndTime": "2021/9/23 P.M. 05:11:01",
    "TestLength": 1,
    "TotalChars": 302,
    "GoodChars": 278,
    "TotalBack": 14,
    "WrongWords": ["and", "attach", "in", "listeners"],
    "WrongChars": [
      "s",
      "d",
      "a",
      "Spaces",
      "i",
      "n",
      "Spaces",
      "o",
      "p",
      "Spaces",
      "c",
      "a",
      "c",
      "e",
      "v",
      "a",
      "l",
      "n",
      "e",
      "r",
      "s",
      "Spaces",
      "e",
      "d"
    ]
  },
  {
    "TestEndTime": "2021/9/23 P.M. 05:53:40",
    "TestLength": 3,
    "TotalChars": 852,
    "GoodChars": 810,
    "TotalBack": 31,
    "WrongWords": ["footprint", "worldwide", "findings"],
    "WrongChars": [
      "p",
      "r",
      "i",
      "n",
      "t",
      "w",
      "d",
      "e",
      "v",
      "c",
      "t",
      "l",
      "a",
      "g",
      "u",
      "o",
      "r",
      "u",
      "o",
      "g",
      "s",
      "h",
      "s",
      "p",
      "k",
      "r",
      "n",
      "o",
      "d",
      "t",
      "e",
      "l",
      "m",
      "t",
      "o",
      "r",
      "r",
      "m",
      "e",
      "r",
      "r",
      "r"
    ]
  },
  {
    "TestEndTime": "2021/9/23 P.M. 06:57:18",
    "TestLength": 6,
    "TotalChars": 1708,
    "GoodChars": 1617,
    "TotalBack": 76,
    "WrongWords": ["making", "different", "you", "fungus", "this"],
    "WrongChars": [
      "n",
      "Spaces",
      "s",
      "e",
      "n",
      "g",
      "i",
      "i",
      "c",
      "Spaces",
      "u",
      "b",
      "l",
      "m",
      "a",
      "k",
      "i",
      "n",
      "g",
      "r",
      "p",
      "e",
      "Spaces",
      "m",
      "u",
      "i",
      "d",
      "t",
      "Spaces",
      "l",
      "c",
      "i",
      "l",
      "v",
      "o",
      "Spaces",
      "y",
      "e",
      "n",
      "g",
      "n",
      "i",
      "a",
      "c",
      "d",
      "b",
      "d",
      "g",
      "e",
      "s",
      "i",
      "d",
      "n",
      "e",
      "o",
      "a",
      "s",
      "d",
      "Spaces",
      "r",
      "e",
      "o",
      "u",
      "Spaces",
      "h",
      "Spaces",
      "h",
      "c",
      "s",
      "Spaces",
      "y",
      "y",
      "a",
      "t",
      "g",
      "v",
      "i",
      "d",
      "m",
      "o",
      "s",
      "e",
      "d",
      "Spaces",
      "r",
      "i",
      "s",
      "Spaces",
      "v",
      "s",
      "g"
    ]
  },
  {
    "TestEndTime": "2021/9/23 P.M. 07:10:44",
    "TestLength": 1,
    "TotalChars": 317,
    "GoodChars": 313,
    "TotalBack": 4,
    "WrongWords": [],
    "WrongChars": ["b", "Spaces", "s", "i"]
  },
  {
    "TestEndTime": "2021/9/27 P.M. 12:00:31",
    "TestLength": 3,
    "TotalChars": 839,
    "GoodChars": 783,
    "TotalBack": 46,
    "WrongWords": ["of", "marvellous", "narcotic", "and"],
    "WrongChars": [
      "Spaces",
      "r",
      "a",
      "a",
      "z",
      "f",
      "o",
      "o",
      "f",
      "e",
      "o",
      "l",
      "s",
      "u",
      "u",
      "c",
      "o",
      "t",
      "i",
      "c",
      "h",
      "t",
      "g",
      "n",
      "n",
      "d",
      "a",
      "s",
      "u",
      "t",
      "s",
      "e",
      "i",
      "e",
      "o",
      "r",
      "b",
      "Spaces",
      "t",
      "b",
      "r",
      "p",
      "p",
      "e",
      "l",
      "l",
      "e",
      "h",
      "a",
      "s",
      "f",
      "t",
      "r",
      "u",
      "o",
      "h"
    ]
  },
  {
    "TestEndTime": "2021/9/27 P.M. 12:01:44",
    "TestLength": 1,
    "TotalChars": 274,
    "GoodChars": 256,
    "TotalBack": 18,
    "WrongWords": [],
    "WrongChars": [
      "t",
      "n",
      "e",
      "e",
      "g",
      "r",
      "a",
      "e",
      "e",
      "h",
      "s",
      "l",
      "a",
      "i",
      "c",
      "d",
      "i",
      "m"
    ]
  },
  {
    "TestEndTime": "2021/9/27 P.M. 12:02:51",
    "TestLength": 1,
    "TotalChars": 298,
    "GoodChars": 288,
    "TotalBack": 7,
    "WrongWords": ["particular", "something"],
    "WrongChars": ["Spaces", "e", "m", "o", "v", "a", "s", "b", "n", "g"]
  },
  {
    "TestEndTime": "2021/9/27 P.M. 12:14:23",
    "TestLength": 5,
    "TotalChars": 1464,
    "GoodChars": 1389,
    "TotalBack": 43,
    "WrongWords": [
      "anyone",
      "something",
      "was",
      "weakened",
      "drizzling",
      "drizzle",
      "usually",
      "amount",
      "something",
      "differece",
      "instructions",
      "by",
      "to",
      "apologize"
    ],
    "WrongChars": [
      "o",
      "n",
      "e",
      "Spaces",
      "t",
      "g",
      "a",
      "n",
      "g",
      "b",
      "c",
      "a",
      "s",
      "a",
      "r",
      "n",
      "g",
      "z",
      "l",
      "e",
      "Spaces",
      "l",
      "Spaces",
      "y",
      "y",
      "m",
      "m",
      "i",
      "a",
      "o",
      "a",
      "o",
      "l",
      "a",
      "m",
      "o",
      "u",
      "n",
      "t",
      "o",
      "n",
      "g",
      "c",
      "e",
      "Spaces",
      "s",
      "r",
      "e",
      "n",
      "o",
      "b",
      "o",
      "r",
      "o",
      "t",
      "c",
      "p",
      "m",
      "o",
      "c",
      "y",
      "Spaces",
      "a",
      "t",
      "o",
      "l",
      "o",
      "c",
      "d",
      "a",
      "i",
      "u",
      "c",
      "u",
      "j"
    ]
  },
  {
    "TestEndTime": "2021/9/27 P.M. 12:22:41",
    "TestLength": 6,
    "TotalChars": 1712,
    "GoodChars": 1586,
    "TotalBack": 105,
    "WrongWords": [
      "organs",
      "the",
      "particular",
      "money",
      "to",
      "ferment",
      "working",
      "special",
      "down",
      "ussr"
    ],
    "WrongChars": [
      "a",
      "n",
      "o",
      "l",
      "a",
      "s",
      "h",
      "t",
      "t",
      "o",
      "Spaces",
      "l",
      "i",
      "h",
      "e",
      "c",
      "a",
      "m",
      "o",
      "n",
      "e",
      "y",
      "o",
      "r",
      "t",
      "o",
      "j",
      "c",
      "n",
      "t",
      "h",
      "h",
      "i",
      "t",
      "a",
      "u",
      "h",
      "e",
      "r",
      "n",
      "g",
      "u",
      "l",
      "a",
      "l",
      "a",
      "t",
      "u",
      "s",
      "t",
      "u",
      "o",
      "t",
      "a",
      "m",
      "m",
      "Spaces",
      "Spaces",
      "c",
      "i",
      "a",
      "l",
      "n",
      "a",
      "r",
      "b",
      "c",
      "n",
      "g",
      "s",
      "a",
      "r",
      "c",
      "e",
      "r",
      "i",
      "d",
      "a",
      "Spaces",
      "d",
      "i",
      "w",
      "o",
      "l",
      "s",
      "w",
      "o",
      "h",
      "r",
      "e",
      "h",
      "o",
      "p",
      "Spaces",
      "i",
      "i",
      "e",
      "b",
      "w",
      "n",
      "Spaces",
      "e",
      "s",
      "a",
      "x",
      "o",
      "e",
      "m",
      "y",
      "e",
      "a",
      "u",
      "l",
      "k",
      "c",
      "o",
      "n",
      "i",
      "a",
      "i",
      "t",
      "n",
      "r",
      "o",
      "e",
      "e"
    ]
  },
  {
    "TestEndTime": "2021/9/27 P.M. 12:33:41",
    "TestLength": 10,
    "TotalChars": 2776,
    "GoodChars": 2592,
    "TotalBack": 126,
    "WrongWords": [
      "taxes",
      "sometimes",
      "a",
      "people",
      "before",
      "killing",
      "employed",
      "triangular",
      "is",
      "inflated",
      "trunk",
      "example",
      "piercing",
      "drizzle",
      "rain",
      "something",
      "particular",
      "emissions",
      "inquiry",
      "linesman",
      "a",
      "something",
      "through",
      "through"
    ],
    "WrongChars": [
      "x",
      "o",
      "m",
      "o",
      "s",
      "e",
      "s",
      "a",
      "Spaces",
      "t",
      "a",
      "Spaces",
      "a",
      "e",
      "l",
      "e",
      "Spaces",
      "e",
      "l",
      "i",
      "t",
      "r",
      "o",
      "r",
      "i",
      "e",
      "e",
      "t",
      "a",
      "o",
      "t",
      "a",
      "u",
      "o",
      "r",
      "e",
      "k",
      "o",
      "y",
      "e",
      "d",
      "h",
      "r",
      "e",
      "t",
      "a",
      "s",
      "l",
      "b",
      "i",
      "t",
      "a",
      "s",
      "u",
      "g",
      "n",
      "i",
      "a",
      "d",
      "s",
      "e",
      "d",
      "Spaces",
      "u",
      "n",
      "k",
      "u",
      "m",
      "m",
      "a",
      "e",
      "l",
      "b",
      "e",
      "c",
      "e",
      "p",
      "c",
      "e",
      "r",
      "e",
      "Spaces",
      "m",
      "o",
      "r",
      "p",
      "a",
      "e",
      "t",
      "g",
      "d",
      "x",
      "l",
      "e",
      "a",
      "e",
      "n",
      "i",
      "r",
      "i",
      "e",
      "u",
      "e",
      "o",
      "a",
      "z",
      "i",
      "z",
      "l",
      "e",
      "Spaces",
      "i",
      "n",
      "g",
      "Spaces",
      "o",
      "l",
      "l",
      "o",
      "u",
      "l",
      "o",
      "o",
      "i",
      "s",
      "s",
      "i",
      "s",
      "f",
      "i",
      "Spaces",
      "y",
      "q",
      "n",
      "i",
      "q",
      "u",
      "i",
      "r",
      "y",
      "Spaces",
      "s",
      "x",
      "x",
      "i",
      "i",
      "m",
      "a",
      "n",
      "Spaces",
      "t",
      "a",
      "h",
      "a",
      "a",
      "e",
      "e",
      "f",
      "t",
      "r",
      "e",
      "e",
      "a",
      "Spaces",
      "k",
      "s",
      "m",
      "e",
      "t",
      "h",
      "i",
      "n",
      "g",
      "y",
      "f",
      "l",
      "a",
      "a",
      "Spaces",
      "n",
      "o",
      "r",
      "g",
      "h"
    ]
  },
  {
    "TestEndTime": "2021/9/27 P.M. 12:44:57",
    "TestLength": 1,
    "TotalChars": 311,
    "GoodChars": 294,
    "TotalBack": 10,
    "WrongWords": ["while", "people"],
    "WrongChars": [
      "w",
      "h",
      "i",
      "l",
      "e",
      "Spaces",
      "y",
      "l",
      "s",
      "i",
      "l",
      "e",
      "t",
      "s",
      "g",
      "n",
      "o"
    ]
  },
  {
    "TestEndTime": "2021/9/27 P.M. 12:46:03",
    "TestLength": 1,
    "TotalChars": 304,
    "GoodChars": 286,
    "TotalBack": 18,
    "WrongWords": [],
    "WrongChars": [
      "a",
      "o",
      "d",
      "a",
      "l",
      "u",
      "o",
      "Spaces",
      "t",
      "n",
      "s",
      "t",
      "n",
      "e",
      "r",
      "u",
      "o",
      "t"
    ]
  },
  {
    "TestEndTime": "2021/9/27 P.M. 02:47:25",
    "TestLength": 1,
    "TotalChars": 305,
    "GoodChars": 290,
    "TotalBack": 13,
    "WrongWords": [],
    "WrongChars": [
      "o",
      "h",
      "s",
      "t",
      "i",
      "w",
      "h",
      "u",
      "e",
      "c",
      "y",
      "n",
      "a",
      "n",
      "g"
    ]
  },
  {
    "TestEndTime": "2021/9/27 P.M. 02:56:00",
    "TestLength": 7,
    "TotalChars": 2120,
    "GoodChars": 2004,
    "TotalBack": 99,
    "WrongWords": [
      "shattered",
      "she",
      "the",
      "sometimes",
      "to",
      "from",
      "you",
      "yourself"
    ],
    "WrongChars": [
      "g",
      "e",
      "m",
      "Spaces",
      "e",
      "l",
      "a",
      "Spaces",
      "k",
      "e",
      "i",
      "s",
      "s",
      "u",
      "h",
      "t",
      "e",
      "p",
      "d",
      "a",
      "h",
      "e",
      "Spaces",
      "i",
      "f",
      "s",
      "l",
      "y",
      "a",
      "Spaces",
      "v",
      "s",
      "f",
      "n",
      "a",
      "e",
      "Spaces",
      "Spaces",
      "e",
      "r",
      "a",
      "e",
      "g",
      "a",
      "e",
      "g",
      "d",
      "t",
      "a",
      "h",
      "h",
      "e",
      "Spaces",
      "t",
      "e",
      "e",
      "s",
      "n",
      "y",
      "i",
      "w",
      "t",
      "o",
      "o",
      "t",
      "s",
      "s",
      "i",
      "Spaces",
      "g",
      "n",
      "i",
      "h",
      "t",
      "e",
      "m",
      "o",
      "s",
      "r",
      "r",
      "e",
      "n",
      "e",
      "t",
      "o",
      "t",
      "b",
      "c",
      "a",
      "Spaces",
      "Spaces",
      "b",
      "Spaces",
      "Spaces",
      "Spaces",
      "b",
      "o",
      "u",
      "Spaces",
      "f",
      "o",
      "r",
      "u",
      "o",
      "y",
      "b",
      "i",
      "o",
      "c",
      "u",
      "o",
      "b",
      "Spaces",
      "d",
      "Spaces",
      "Spaces"
    ]
  },
  {
    "TestEndTime": "2021/9/28 A.M. 01:50:13",
    "TestLength": 1,
    "TotalChars": 287,
    "GoodChars": 270,
    "TotalBack": 14,
    "WrongWords": ["can", "fly"],
    "WrongChars": [
      "s",
      "s",
      "p",
      "a",
      "m",
      "d",
      "c",
      "a",
      "n",
      "Spaces",
      "y",
      "Spaces",
      "g",
      "i",
      "a",
      "l",
      "b"
    ]
  },
  {
    "TestEndTime": "2021/9/28 A.M. 01:51:20",
    "TestLength": 1,
    "TotalChars": 300,
    "GoodChars": 288,
    "TotalBack": 12,
    "WrongWords": [],
    "WrongChars": [
      "Spaces",
      "a",
      "h",
      "c",
      "e",
      "e",
      "i",
      "Spaces",
      "o",
      "t",
      "Spaces",
      "e"
    ]
  },
  {
    "TestEndTime": "2021/9/28 A.M. 01:57:59",
    "TestLength": 2,
    "TotalChars": 537,
    "GoodChars": 508,
    "TotalBack": 29,
    "WrongWords": [],
    "WrongChars": [
      "p",
      "g",
      "o",
      "l",
      "n",
      "t",
      "o",
      "e",
      "Spaces",
      "r",
      "e",
      "v",
      "s",
      "e",
      "h",
      "i",
      "s",
      "e",
      "a",
      "e",
      "h",
      "w",
      "s",
      "i",
      "a",
      "d",
      "u",
      "l",
      "a"
    ]
  },
  {
    "TestEndTime": "2021/9/28 P.M. 11:18:00",
    "TestLength": 3,
    "TotalChars": 850,
    "GoodChars": 817,
    "TotalBack": 27,
    "WrongWords": ["especially", "bites", "situation", "lying"],
    "WrongChars": [
      "t",
      "t",
      "e",
      "o",
      "Spaces",
      "s",
      "u",
      "o",
      "e",
      "e",
      "g",
      "t",
      "e",
      "s",
      "c",
      "i",
      "e",
      "n",
      "s",
      "o",
      "m",
      "n",
      "r",
      "s",
      "i",
      "i",
      "r",
      "a",
      "a",
      "n",
      "g",
      "k",
      "g"
    ]
  },
  {
    "TestEndTime": "2021/9/29 A.M. 11:53:49",
    "TestLength": 1,
    "TotalChars": 303,
    "GoodChars": 285,
    "TotalBack": 11,
    "WrongWords": ["the", "indecency", "an"],
    "WrongChars": [
      "t",
      "h",
      "e",
      "Spaces",
      "c",
      "m",
      "s",
      "d",
      "e",
      "v",
      "Spaces",
      "a",
      "n",
      "t",
      "i",
      "a",
      "e",
      "b"
    ]
  },
  {
    "TestEndTime": "2021/9/29 A.M. 11:59:12",
    "TestLength": 5,
    "TotalChars": 1488,
    "GoodChars": 1394,
    "TotalBack": 64,
    "WrongWords": [
      "the",
      "in",
      "order",
      "request",
      "peek",
      "my",
      "were",
      "something",
      "country",
      "other",
      "over",
      "sometimes",
      "abuser"
    ],
    "WrongChars": [
      "e",
      "h",
      "h",
      "t",
      "e",
      "e",
      "r",
      "i",
      "k",
      "e",
      "n",
      "n",
      "p",
      "n",
      "Spaces",
      "u",
      "e",
      "e",
      "t",
      "u",
      "o",
      "y",
      "w",
      "y",
      "r",
      "a",
      "p",
      "i",
      "c",
      "y",
      "n",
      "o",
      "r",
      "d",
      "e",
      "r",
      "Spaces",
      "Spaces",
      "r",
      "e",
      "q",
      "u",
      "e",
      "s",
      "t",
      "a",
      "s",
      "y",
      "k",
      "e",
      "e",
      "x",
      "a",
      "Spaces",
      "i",
      "r",
      "Spaces",
      "e",
      "n",
      "g",
      "t",
      "n",
      "b",
      "c",
      "n",
      "t",
      "h",
      "h",
      "e",
      "m",
      "u",
      "o",
      "t",
      "e",
      "g",
      "d",
      "c",
      "h",
      "i",
      "v",
      "m",
      "e",
      "w",
      "v",
      "e",
      "r",
      "t",
      "o",
      "Spaces",
      "t",
      "s",
      "e",
      "s",
      "Spaces"
    ]
  },
  {
    "TestEndTime": "2021/9/29 P.M. 12:02:09",
    "TestLength": 1,
    "TotalChars": 319,
    "GoodChars": 306,
    "TotalBack": 7,
    "WrongWords": ["refuses", "was", "verbs"],
    "WrongChars": [
      "s",
      "a",
      "s",
      "b",
      "s",
      "Spaces",
      "Spaces",
      "h",
      "a",
      "t",
      "n",
      "m",
      "a"
    ]
  },
  {
    "TestEndTime": "2021/9/29 P.M. 12:03:16",
    "TestLength": 1,
    "TotalChars": 304,
    "GoodChars": 289,
    "TotalBack": 14,
    "WrongWords": ["big"],
    "WrongChars": [
      "Spaces",
      "n",
      "a",
      "f",
      "s",
      "g",
      "l",
      "p",
      "l",
      "e",
      "e",
      "p",
      "a",
      "e",
      "m"
    ]
  },
  {
    "TestEndTime": "2021/9/29 P.M. 12:04:33",
    "TestLength": 1,
    "TotalChars": 331,
    "GoodChars": 319,
    "TotalBack": 9,
    "WrongWords": ["by", "object"],
    "WrongChars": [
      "l",
      "o",
      "s",
      "e",
      "b",
      "y",
      "o",
      "l",
      "n",
      "a",
      "Spaces",
      "o"
    ]
  },
  {
    "TestEndTime": "2021/9/29 P.M. 02:58:08",
    "TestLength": 1,
    "TotalChars": 324,
    "GoodChars": 317,
    "TotalBack": 7,
    "WrongWords": [],
    "WrongChars": ["e", "t", "n", "t", "a", "o", "b"]
  },
  {
    "TestEndTime": "2021/9/29 P.M. 03:03:19",
    "TestLength": 5,
    "TotalChars": 1477,
    "GoodChars": 1413,
    "TotalBack": 46,
    "WrongWords": ["uttering", "be", "term", "cutting", "off", "is", "that"],
    "WrongChars": [
      "Spaces",
      "Spaces",
      "Spaces",
      "r",
      "r",
      "u",
      "o",
      "t",
      "e",
      "e",
      "b",
      "l",
      "a",
      "n",
      "o",
      "e",
      "r",
      "i",
      "n",
      "g",
      "l",
      "s",
      "g",
      "i",
      "Spaces",
      "t",
      "c",
      "e",
      "j",
      "p",
      "s",
      "n",
      "i",
      "Spaces",
      "i",
      "u",
      "e",
      "Spaces",
      "h",
      "e",
      "b",
      "o",
      "o",
      "e",
      "l",
      "p",
      "p",
      "c",
      "c",
      "u",
      "t",
      "t",
      "i",
      "n",
      "g",
      "f",
      "g",
      "s",
      "t",
      "h",
      "c",
      "a",
      "c",
      "a"
    ]
  },
  {
    "TestEndTime": "2021/9/29 P.M. 05:15:35",
    "TestLength": 1,
    "TotalChars": 313,
    "GoodChars": 307,
    "TotalBack": 6,
    "WrongWords": [],
    "WrongChars": ["a", "r", "a", "l", "a", "g"]
  },
  {
    "TestEndTime": "2021/9/29 P.M. 05:21:58",
    "TestLength": 6,
    "TotalChars": 1805,
    "GoodChars": 1736,
    "TotalBack": 51,
    "WrongWords": [
      "up",
      "football",
      "study",
      "judge",
      "group",
      "manners",
      "when",
      "plant",
      "an"
    ],
    "WrongChars": [
      "c",
      "a",
      "s",
      "b",
      "e",
      "p",
      "b",
      "a",
      "l",
      "l",
      "l",
      "g",
      "o",
      "l",
      "k",
      "e",
      "r",
      "s",
      "t",
      "u",
      "d",
      "y",
      "r",
      "u",
      "r",
      "e",
      "v",
      "u",
      "t",
      "o",
      "u",
      "b",
      "p",
      "Spaces",
      "m",
      "s",
      "t",
      "e",
      "d",
      "i",
      "s",
      "l",
      "c",
      "g",
      "u",
      "r",
      "o",
      "t",
      "a",
      "f",
      "r",
      "i",
      "e",
      "h",
      "c",
      "Spaces",
      "n",
      "o",
      "c",
      "s",
      "h",
      "n",
      "t",
      "Spaces",
      "v",
      "a",
      "d",
      "r",
      "i"
    ]
  }
,{"TestEndTime":"2021/9/29 P.M. 05:31:03","TestLength":1,"TotalChars":308,"GoodChars":300,"TotalBack":5,"WrongWords":["an","this"],"WrongChars":["Spaces","n","i","p","e","c","i","s"]},{"TestEndTime":"2021/9/29 P.M. 05:36:13","TestLength":5,"TotalChars":1521,"GoodChars":1467,"TotalBack":44,"WrongWords":["have","reducing","the","manual","jumped"],"WrongChars":["t","s","c","l","p","p","s","u","e","v","e","n","n","g","t","s","e","f","Spaces","c","i","l","f","u","h","e","s","i","s","u","p","s","l","p","e","d","Spaces","t","u","o","e","t","a","a","b","v","Spaces","s","Spaces","e","n","o","b","e"]}]  