[
  {
    "DateTime": "2021/8/16 P.M. 05:12:30",
    "TestLength": 1,
    "TotalChars": 251,
    "GoodChars": 249,
    "TotalBack": 18,
    "WrongWords": ["kill", "deceased"],
    "WrongChars": [
      "i",
      "f",
      "i",
      "t",
      "n",
      "k",
      "m",
      "i",
      "n",
      "c",
      "e",
      "h",
      "s",
      "s",
      "d",
      "k",
      "b",
      "r",
      "e",
      "g"
    ]
  },
  {
    "DateTime": "2021/8/16 P.M. 05:28:09",
    "TestLength": 1,
    "TotalChars": 247,
    "GoodChars": 247,
    "TotalBack": 13,
    "WrongWords": [],
    "WrongChars": [
      "l",
      "i",
      "d",
      "d",
      "m",
      "h",
      "c",
      "h",
      "d",
      "d",
      "e",
      "o",
      "d"
    ]
  },
  {
    "DateTime": "2021/8/16 P.M. 05:29:34",
    "TestLength": 1,
    "TotalChars": 280,
    "GoodChars": 280,
    "TotalBack": 4,
    "WrongWords": [],
    "WrongChars": ["e", "t", "e", "s"]
  },
  {
    "DateTime": "2021/8/16 P.M. 05:32:12",
    "TestLength": 2,
    "TotalChars": 538,
    "GoodChars": 530,
    "TotalBack": 16,
    "WrongWords": ["the", "sanitation", "a"],
    "WrongChars": [
      "t",
      "h",
      "e",
      "l",
      "e",
      "e",
      "e",
      "i",
      "c",
      "i",
      "u",
      "l",
      "a",
      "a",
      "t",
      "i",
      "o",
      "n",
      "a",
      "t",
      "s",
      "i",
      "e",
      "a"
    ]
  }
]
