{
  "nerve": [""],
  "insulin": [""],
  "enzymes": [""],
  "activate": [""],
  "stimulate": [""],
  "strike": [""],
  "": [""],
  "": [""],
  "": [""],
  "": [""],
  "": [""],
  "": [""],
  "": [""],
  "": [""],
  "": [""],
  "": [""],
  "": [""],
  "": [""],
  "": [""],
  "": [""],
  "": [""],
  "": [""],
  "": [""],
  "": [""],
  "": [""],
  "": [""],
  "": [""],
  "": [""],
  "": [""],
  "": [""],
  "": [""],
  "": [""],
  "": [""],
  "": [""],
  "": [""],
  "": [""],
  "": [""],
  "": [""],
  "": [""],
  "": [""],
  "": [""],
  "": [""],
  "": [""],
  "": [""],
  "": [""],
  "": [""],
  "": [""],
  "": [""]
}
