{
  "": [""],
  "evaporation": [""],
  "electrolyte": [""],
  "surplus": [""],
  "imbalance": [""],
  "hypernatremia": [""],
  "bloated": [""],
  "abruptly": [""],
  "sore": [""],
  "ketone": [""],
  "nitroglycerine": [
    "",
    {
      "nitrate": [""],
      "glycerol": [""],
      "glycerine": [""]
    }
  ],
  "sterol": [""],
  "methyl": [""],
  "biodiesel": [
    "",
    {
      "diesel": [""]
    }
  ],
  "lanolin": [""],
  "cholesterol": [""],
  "stearic": [""],
  "palmitic": [""],
  "oleic": [""],
  "": [""],
  "": [""],
  "": [""],
  "": [""],
  "": [""],
  "": [""],
  "": [""],
  "": [""],
  "": [""],
  "": [""],
  "": [""],
  "": [""],
  "": [""],
  "": [""],
  "": [""],
  "": [""],
  "": [""],
  "": [""],
  "": [""],
  "": [""],
  "": [""],
  "": [""],
  "": [""],
  "": [""],
  "": [""],
  "": [""],
  "": [""],
  "": [""],
  "": [""],
  "": [""],
  "": [""],
  "": [""],
  "": [""],
  "": [""],
  "": [""],
  "": [""],
  "": [""],
  "": [""],
  "": [""],
  "": [""],
  "": [""],
  "": [""],
  "": [""],
  "": [""],
  "": [""],
  "": [""],
  "": [""],
  "": [""],
  "": [""],
  "": [""],
  "": [""],
  "": [""],
  "": [""]
}
